gym_simplegrid/__init__.py
gym_simplegrid/envs/__init__.py
gym_simplegrid/envs/simple_grid.py
gym_simplegrid-1.0.6.dist-info/LICENSE
gym_simplegrid-1.0.6.dist-info/METADATA
gym_simplegrid-1.0.6.dist-info/WHEEL
gym_simplegrid-1.0.6.dist-info/top_level.txt
gym_simplegrid-1.0.6.dist-info/RECORD
