Metadata-Version: 2.1
Name: gym_simplegrid
Version: 1.0.6
Summary: Simple Gridworld Environment for Gymnasium
Home-page: https://github.com/damat-le/gym-simplegrid
Author: Leo D'Amato
Author-email: leo.damato.dev@gmail.com
Keywords: reinforcement learning,environment,gridworld,agent,rl,openaigym,openai-gym,gym,gymnasium,farama-foundation
Classifier: Programming Language :: Python :: 3
Classifier: Operating System :: OS Independent
Requires-Python: >=3.7
License-File: LICENSE
Requires-Dist: gymnasium
Requires-Dist: matplotlib
